olamaps/__init__.py
olamaps/client.py
olamaps/exceptions.py
olamaps/places.py
olamaps/routing.py
olamaps-0.5.2.dist-info/LICENSE
olamaps-0.5.2.dist-info/METADATA
olamaps-0.5.2.dist-info/WHEEL
olamaps-0.5.2.dist-info/RECORD
