Metadata-Version: 2.1
Name: olamaps
Version: 0.5.2
Summary: Python client library for Ola Maps API Web Services
Home-page: https://github.com/adayush/olamaps-python
License: MIT
Keywords: ola,maps
Author: adayush
Author-email: adayush0@gmail.com
Requires-Python: >=3.9,<4.0
Classifier: License :: OSI Approved :: MIT License
Classifier: Programming Language :: Python :: 3
Classifier: Programming Language :: Python :: 3.9
Classifier: Programming Language :: Python :: 3.10
Classifier: Programming Language :: Python :: 3.11
Classifier: Programming Language :: Python :: 3.12
Requires-Dist: httpx (>=0.27.0,<0.28.0)
Project-URL: Issues, https://github.com/adayush/olamaps-python/issues
Project-URL: Repository, https://github.com/adayush/olamaps-python
